[
    {
        "title": "金融探偵",
        "text": [
            {"paragraph": ""}
        ],
        "page":""
    },
    {
        "title": "銀行はやめたけど",
        "text": [
            {"paragraph": "　半分ジョークだったが、二人はにこりともしなかった。何も聞こえなかったかのように、表情ひとつ変わらない。"}
        ],
        "page":"12"
    },
    {
        "title": "銀行はやめたけど",
        "text": [
            {"paragraph": "「なんとかなりませんか？」"},
            {"paragraph": "　なんとか、か。"},
            {"paragraph": "　そのなんとかが曲者だ。なんとか出来るものなら、してやりたいさ。世の中には、そう簡単にいかないことはいくらでもある。現に俺の職探しだってそうじゃないかと、次郎は思ったが言えなかった。だが、"},
            {"paragraph": "「大原さんしか、頼る人がいないんです」"},
            {"paragraph": "　その一言が、袖の下に隠された切れ味鋭い小刀のように次郎の心臓を一突きにした。失業中で、宙ぶらりんで、自分の明日のことすらままならぬこの俺を頼るというのか。"}
        ],
        "page":"23"
    }
]